{
  "periodo": "2018-07",
  "total_publicacoes": 2,
  "publicacoes": [
    {
      "id": "17931400879182266",
      "timestamp": "2018-07-10T14:15:27+0000",
      "periodo": "2018-07",
      "media_type": "IMAGE",
      "media_product_type": "FEED",
      "caption": "Estoque renovado porque tudo mundo quer o queridinho da faxina #oxypower #faxinando #limpezaprofissional #limpatudo",
      "permalink": "https://www.instagram.com/p/BlDdvlGlktZ/",
      "media_url": "https://scontent-iad3-1.cdninstagram.com/v/t51.82787-15/629364671_18397845514182266_4332443634037568337_n.jpg?stp=dst-jpg_e35_tt6&_nc_cat=110&ccb=7-5&_nc_sid=18de74&efg=eyJlZmdfdGFnIjoiRkVFRC5iZXN0X2ltYWdlX3VybGdlbi5DMyJ9&_nc_ohc=lTpEs7tugJkQ7kNvwFzOwOI&_nc_oc=AdqAP6qc03M2vdyqDAKlrrZD24JXOefVddkfi15glZ6zzQFeJ55Cj8a920D0s8PdTTA&_nc_zt=23&_nc_ht=scontent-iad3-1.cdninstagram.com&edm=ANo9K5cEAAAA&_nc_gid=QGPCewl8sIAY7oy4lFqdow&_nc_tpa=Q5bMBQH8laGTe4NCpv55PT3D0dKWEcrY6TBpH7vJ5PaAWgBG6uhcgVY45vjp1nXJCP0wop78Kzp9EKhRrQ&oh=00_AQDzlbaKMWfdrVxHzvpp24sV5EufIstTFR23L1zKKc44Ag&oe=6A67CB1F",
      "thumbnail_url": null,
      "like_count": 25,
      "comments_count": 0,
      "children": [],
      "insights": {
        "reach": 2,
        "views": 0,
        "saved": 0,
        "shares": 0,
        "total_interactions": 25
      },
      "coletado_em": "2026-07-23T11:26:43.132Z"
    },
    {
      "id": "17941316989091182",
      "timestamp": "2018-07-20T20:30:18+0000",
      "periodo": "2018-07",
      "media_type": "IMAGE",
      "media_product_type": "FEED",
      "caption": "Lixeiras com garantia e proteção UV",
      "permalink": "https://www.instagram.com/p/Bld4l0VgbYp/",
      "media_url": "https://scontent-iad3-2.cdninstagram.com/v/t51.82787-15/631754717_18376652278091182_2199827653595267859_n.jpg?stp=dst-jpg_e35_tt6&_nc_cat=103&ccb=7-5&_nc_sid=18de74&efg=eyJlZmdfdGFnIjoiRkVFRC5iZXN0X2ltYWdlX3VybGdlbi5DMyJ9&_nc_ohc=2gXWl6saAG0Q7kNvwHkzSoz&_nc_oc=Adq80wsrJPUFLkpBs5m4d2QYWemyGr_SwHWd3m8tEnZYVp8oIjt_AsUAloNabfiuBWs&_nc_zt=23&_nc_ht=scontent-iad3-2.cdninstagram.com&edm=ANo9K5cEAAAA&_nc_gid=QGPCewl8sIAY7oy4lFqdow&_nc_tpa=Q5bMBQFJBCMXddKky7TknQYAil2l2bK8A3XxwrniTbOzSJXRaVo94e9YiB9a2pmkM1JU5OuX4VBalaMMdw&oh=00_AQCFarbHzP1tR58yXKwcmsuEKINbD-C-6C-XB9rsCPWsCQ&oe=6A67B5B9",
      "thumbnail_url": null,
      "like_count": 11,
      "comments_count": 0,
      "children": [],
      "insights": {
        "reach": 1,
        "views": 0,
        "saved": 2,
        "shares": 0,
        "total_interactions": 13
      },
      "coletado_em": "2026-07-23T11:26:42.923Z"
    }
  ]
}